fastfold/__init__.py
fastfold/cli.py
fastfold/client.py
fastfold/errors.py
fastfold/http.py
fastfold/models.py
fastfold/services/__init__.py
fastfold/services/fold.py
fastfold/services/jobs.py
fastfold_ai-0.1.3.dist-info/METADATA
fastfold_ai-0.1.3.dist-info/WHEEL
fastfold_ai-0.1.3.dist-info/entry_points.txt
fastfold_ai-0.1.3.dist-info/RECORD
