Metadata-Version: 2.4
Name: fastfold-ai
Version: 0.1.3
Summary: Official Python SDK and CLI for the FastFold API
Project-URL: Homepage, https://fastfold.ai
Project-URL: Repository, https://fastfold.ai
Author-email: FastFold <hello@fastfold.ai>
License-Expression: Apache-2.0
Keywords: ai,cli,fastfold,folding,protein,sdk
Classifier: Environment :: Console
Classifier: Intended Audience :: Science/Research
Classifier: License :: OSI Approved :: Apache Software License
Classifier: Programming Language :: Python :: 3
Classifier: Programming Language :: Python :: 3 :: Only
Classifier: Topic :: Scientific/Engineering :: Bio-Informatics
Requires-Python: >=3.8
Requires-Dist: requests<3,>=2.31.0
